{
  "teachers": [
    {
      "teacher_id": "1090300173",
      "name": "Shibbir",
      "college_name": "Gazipur Govt College ",
      "mobileNo": "0173",
      "eiin": "109030",
      "created_model_tests": [
        {
          "teacher_id": "1090300173",
          "test_name": "sh1",
          "chapter_name": "All Chapters",
          "total_questions": 15,
          "difficulty": "All",
          "last_date": "2025-10-09",
          "validity_time_minutes": 25,
          "is_allowed": true,
          "selected_student_ids": [
            "2027101",
            "11467820261140"
          ],
          "model_test_id": "16",
          "participants": []
        }
      ]
    }
  ]
}
