{
  "leaderboard": [
    {
      "id": "20263",
      "name": "ROKEYA AKTER MIM",
      "group": "SCIENCE",
      "xp_points": 1500,
      "level": "Pro",
      "last_updated": "2025-09-15T22:00:00Z"
    },
    {
      "id": "20262",
      "name": "SHEIKH RAYEEDAH RAISA",
      "group": "BUSINESS STUDIES",
      "xp_points": 950,
      "level": "Beginner",
      "last_updated": "2025-09-15T22:00:00Z"
    },
    {
      "id": "1090302026125",
      "name": "JARIN TASNIM MIM",
      "group": "SCIENCE",
      "xp_points": 340,
      "level": "Newcomer",
      "last_updated": "2025-10-02 07:41:12"
    },
    {
      "id": "20261",
      "name": "ISRAT JAHAN JUI",
      "group": "BUSINESS STUDIES",
      "xp_points": 107,
      "level": "Intermediate",
      "last_updated": "2025-09-15T22:00:00Z"
    },
    {
      "id": "2027203",
      "name": "NPREMA",
      "group": "HUMANITIES",
      "xp_points": 8,
      "level": "Newcomer",
      "last_updated": "2025-09-21 22:07:04"
    }
  ]
}